lab10/RevCounter.v
module RevCounter( 
    input wire clk,
    input wire rst,
    input wire s,
    output reg [15:0] cnt = 16'h0000,
    output wire Rc
);

    always @(posedge clk) begin
        if (rst) begin
            cnt <= 16'h0000;
        end else begin
            if (s == 1'b0) begin
                cnt <= cnt + 1'b1;
            end else begin
                cnt <= cnt - 1'b1;
            end
        end
    end

    assign Rc = (s == 1'b0) ? (cnt == 16'hFFFF) : (cnt == 16'h0000);

endmodule

lab10/tb_Counter4b.v
`timescale 1ns / 1ps

module tb_RevCounter;

    reg clk;
    reg rst;
    reg s;
    wire [15:0] cnt;
    wire Rc;

    RevCounter uut (
        .clk(clk), 
        .rst(rst), 
        .s(s), 
        .cnt(cnt), 
        .Rc(Rc)
    );

    initial begin
        clk = 0;
        forever #10 clk = ~clk;
    end

    initial begin
        $dumpfile("tb_RevCounter.vcd");
        $dumpvars(0, tb_RevCounter);
    end

    initial begin
        rst = 1;
        s = 0;
        #40;
        
        @(posedge clk);
        #1 rst = 0;
        #100;
        
        @(posedge clk);
        #1 uut.cnt = 16'hFFFE; 
        #60; 
        
        @(posedge clk);
        #1 s = 1;
        #100;
        
        @(posedge clk);
        #1 uut.cnt = 16'h0002;
        #60; 
        
        @(posedge clk);
        #1 rst = 1;
        #20;
        #1 rst = 0;
        
        #100;
        $finish;
    end
      
endmodule

lab10/bIn/tb_RevCounter.vcd
$date
	Thu May 28 20:18:31 2026
$end
$version
	Icarus Verilog
$end
$timescale
	1ps
$end
$scope module tb_RevCounter $end
$var wire 16 ! cnt [15:0] $end
$var wire 1 " Rc $end
$var reg 1 # clk $end
$var reg 1 $ rst $end
$var reg 1 % s $end
$scope module uut $end
$var wire 1 # clk $end
$var wire 1 $ rst $end
$var wire 1 % s $end
$var wire 1 " Rc $end
$var reg 16 & cnt [15:0] $end
$upscope $end
$upscope $end
$enddefinitions $end
$comment Show the parameter values. $end
$dumpall
$end
#0
$dumpvars
b0 &
0%
1$
0#
0"
b0 !
$end
#10000
1#
#20000
0#
#30000
1#
#40000
0#
#50000
1#
#51000
0$
#60000
0#
#70000
b1 !
b1 &
1#
#80000
0#
#90000
b10 !
b10 &
1#
#100000
0#
#110000
b11 !
b11 &
1#
#120000
0#
#130000
b100 !
b100 &
1#
#140000
0#
#150000
b101 !
b101 &
1#
#160000
0#
#170000
b110 !
b110 &
1#
#171000
b1111111111111110 !
b1111111111111110 &
#180000
0#
#190000
1"
b1111111111111111 !
b1111111111111111 &
1#
#200000
0#
#210000
0"
b0 !
b0 &
1#
#220000
0#
#230000
b1 !
b1 &
1#
#240000
0#
#250000
b10 !
b10 &
1#
#251000
1%
#260000
0#
#270000
b1 !
b1 &
1#
#280000
0#
#290000
1"
b0 !
b0 &
1#
#300000
0#
#310000
0"
b1111111111111111 !
b1111111111111111 &
1#
#320000
0#
#330000
b1111111111111110 !
b1111111111111110 &
1#
#340000
0#
#350000
b1111111111111101 !
b1111111111111101 &
1#
#360000
0#
#370000
b1111111111111100 !
b1111111111111100 &
1#
#371000
b10 !
b10 &
#380000
0#
#390000
b1 !
b1 &
1#
#400000
0#
#410000
1"
b0 !
b0 &
1#
#420000
0#
#430000
0"
b1111111111111111 !
b1111111111111111 &
1#
#440000
0#
#450000
b1111111111111110 !
b1111111111111110 &
1#
#451000
1$
#460000
0#
#470000
1"
b0 !
b0 &
1#
#472000
0$
#480000
0#
#490000
0"
b1111111111111111 !
b1111111111111111 &
1#
#500000
0#
#510000
b1111111111111110 !
b1111111111111110 &
1#
#520000
0#
#530000
b1111111111111101 !
b1111111111111101 &
1#
#540000
0#
#550000
b1111111111111100 !
b1111111111111100 &
1#
#560000
0#
#570000
b1111111111111011 !
b1111111111111011 &
1#
