lab6/MyMC14495.v
module MyMC14495(
    input D0, D1, D2, D3,
    input LE,
    input point,
    output reg p,
    output reg a, b, c, d, e, f, g
);

    always @(*) begin
        if (LE == 1'b0) begin
            case({D3, D2, D1, D0})
                4'h0: {a,b,c,d,e,f,g} = 7'b0000001; 
                4'h1: {a,b,c,d,e,f,g} = 7'b1001111; 
                4'h2: {a,b,c,d,e,f,g} = 7'b0010010; 
                4'h3: {a,b,c,d,e,f,g} = 7'b0000110; 
                4'h4: {a,b,c,d,e,f,g} = 7'b1001100; 
                4'h5: {a,b,c,d,e,f,g} = 7'b0100100; 
                4'h6: {a,b,c,d,e,f,g} = 7'b0100000; 
                4'h7: {a,b,c,d,e,f,g} = 7'b0001111; 
                4'h8: {a,b,c,d,e,f,g} = 7'b0000000; 
                4'h9: {a,b,c,d,e,f,g} = 7'b0000100; 
                4'hA: {a,b,c,d,e,f,g} = 7'b0001000; 
                4'hB: {a,b,c,d,e,f,g} = 7'b1100000; 
                4'hC: {a,b,c,d,e,f,g} = 7'b0110001; 
                4'hD: {a,b,c,d,e,f,g} = 7'b1000010; 
                4'hE: {a,b,c,d,e,f,g} = 7'b0110000; 
                4'hF: {a,b,c,d,e,f,g} = 7'b0111000; 
                default: {a,b,c,d,e,f,g} = 7'b1111111;
            endcase
        end else begin
            {a,b,c,d,e,f,g} = 7'b1111111;
        end
        

        if (point == 1'b1) begin
            p = 1'b0;
        end else begin
            p = 1'b1;
        end
    end

endmodule

lab6/MyMC14495_tb.v
`timescale 1ns / 1ps

module MyMC14495_tb();
    reg D0, D1, D2, D3;
    reg LE, point;
    wire p, a, b, c, d, e, f, g;
    
    MyMC14495 uut (
        .D0(D0), .D1(D1), .D2(D2), .D3(D3),
        .LE(LE), .point(point),
        .p(p), .a(a), .b(b), .c(c), .d(d), .e(e), .f(f), .g(g)
    );
    
    integer i;

    initial begin

        $dumpfile("wave.vcd");
        $dumpvars(0, MyMC14495_tb);
        

        LE = 1; point = 0; D3 = 0; D2 = 0; D1 = 0; D0 = 0;
        #20;
        
        LE = 0; point = 1;
        #20;
        
        for (i = 0; i < 16; i = i + 1) begin
            {D3, D2, D1, D0} = i;
            #20;
        end
        
        $finish;
    end
endmodule

lab6/wave.vcd
$date
	Thu Apr  9 10:55:54 2026
$end
$version
	Icarus Verilog
$end
$timescale
	1ps
$end
$scope module MyMC14495_tb $end
$var wire 1 ! p $end
$var wire 1 " g $end
$var wire 1 # f $end
$var wire 1 $ e $end
$var wire 1 % d $end
$var wire 1 & c $end
$var wire 1 ' b $end
$var wire 1 ( a $end
$var reg 1 ) D0 $end
$var reg 1 * D1 $end
$var reg 1 + D2 $end
$var reg 1 , D3 $end
$var reg 1 - LE $end
$var reg 1 . point $end
$var integer 32 / i [31:0] $end
$scope module uut $end
$var wire 1 ) D0 $end
$var wire 1 * D1 $end
$var wire 1 + D2 $end
$var wire 1 , D3 $end
$var wire 1 - LE $end
$var wire 1 . point $end
$var reg 1 ( a $end
$var reg 1 ' b $end
$var reg 1 & c $end
$var reg 1 % d $end
$var reg 1 $ e $end
$var reg 1 # f $end
$var reg 1 " g $end
$var reg 1 ! p $end
$upscope $end
$upscope $end
$enddefinitions $end
$comment Show the parameter values. $end
$dumpall
$end
#0
$dumpvars
bx /
0.
1-
0,
0+
0*
0)
1(
1'
1&
1%
1$
1#
1"
1!
$end
#20000
0!
0(
0'
0&
0%
0$
0#
1.
0-
#40000
b0 /
#60000
1(
1%
1$
1#
1)
b1 /
#80000
0(
1&
0%
0$
0"
1*
0)
b10 /
#100000
0&
1$
1)
b11 /
#120000
1(
1%
0#
1+
0*
0)
b100 /
#140000
0(
1'
0%
1)
b101 /
#160000
0$
1*
0)
b110 /
#180000
0'
1%
1$
1#
1"
1)
b111 /
#200000
0%
0$
0#
0"
1,
0+
0*
0)
b1000 /
#220000
1$
1)
b1001 /
#240000
1%
0$
1*
0)
b1010 /
#260000
1(
1'
0%
1)
b1011 /
#280000
0(
1&
1"
1+
0*
0)
b1100 /
#300000
1(
0'
0&
1#
0"
1)
b1101 /
#320000
0(
1'
1&
0#
1*
0)
b1110 /
#340000
1%
1)
b1111 /
#360000
b10000 /
